yolov7_package/__init__.py
yolov7_package/detect.py
yolov7_package/load_utils.py
yolov7_package/model_utils.py
yolov7_package/models/__init__.py
yolov7_package/models/common.py
yolov7_package/models/experimental.py
yolov7_package/models/yolo.py
yolov7_package/utils/__init__.py
yolov7_package/utils/activations.py
yolov7_package/utils/add_nms.py
yolov7_package/utils/autoanchor.py
yolov7_package/utils/datasets.py
yolov7_package/utils/general.py
yolov7_package/utils/google_utils.py
yolov7_package/utils/loss.py
yolov7_package/utils/metrics.py
yolov7_package/utils/torch_utils.py
yolov7_package/utils/aws/__init__.py
yolov7_package/utils/aws/resume.py
yolov7_package/utils/wandb_logging/__init__.py
yolov7_package/utils/wandb_logging/log_dataset.py
yolov7_package/utils/wandb_logging/wandb_utils.py
test_yolo-0.0.14.dist-info/LICENSE
test_yolo-0.0.14.dist-info/METADATA
test_yolo-0.0.14.dist-info/WHEEL
test_yolo-0.0.14.dist-info/top_level.txt
test_yolo-0.0.14.dist-info/RECORD
