Metadata-Version: 2.1
Name: test-yolo
Version: 0.0.14
Summary: Bindings for yolov7 in one class
Home-page: https://github.com/maxwolf8852/yolov7_package.git
Author: Maxim Volkovskiy
Author-email: maxwolf8852@gmail.com
License: UNKNOWN
Platform: UNKNOWN
Classifier: Programming Language :: Python :: 3.6
Classifier: License :: OSI Approved :: MIT License
Classifier: Operating System :: OS Independent
Requires-Python: >=3.6
License-File: LICENSE
Requires-Dist: pyyaml
Requires-Dist: opencv-python
Requires-Dist: torch
Requires-Dist: torchvision
Requires-Dist: requests
Requires-Dist: wget
Requires-Dist: tqdm
